gaql_console/__init__.py
gaql_console/__main__.py
gaql_console/api_client.py
gaql_console/console.py
gaql_console/context.py
gaql_console/exceptions.py
gaql_console/grammar.py
gaql_console-0.1.9.dist-info/METADATA
gaql_console-0.1.9.dist-info/WHEEL
gaql_console-0.1.9.dist-info/entry_points.txt
gaql_console-0.1.9.dist-info/RECORD
