Metadata-Version: 2.3
Name: gaql-console
Version: 0.1.9
Summary: Google Ads Query Language Interactive Console
License: MIT
Author: Piotr Kilczuk
Author-email: piotr@kilczuk.dev
Requires-Python: >=3.9,<4.0
Classifier: License :: OSI Approved :: MIT License
Classifier: Programming Language :: Python :: 3
Classifier: Programming Language :: Python :: 3.9
Classifier: Programming Language :: Python :: 3.10
Classifier: Programming Language :: Python :: 3.11
Classifier: Programming Language :: Python :: 3.12
Classifier: Programming Language :: Python :: 3.13
Requires-Dist: Pygments (>=2.11.2,<3.0.0)
Requires-Dist: click (>=8.1.7,<9.0.0)
Requires-Dist: google-ads (>=26.0.1,<29.0.0) ; python_version >= "3.8" and python_version < "3.13"
Requires-Dist: prompt-toolkit (>=3.0.47,<4.0.0)
Requires-Dist: toml (>=0.10.2,<0.11.0)
